lazylog/__init__.py
lazylog/lazylog.py
lazylog_python-0.1.0.dist-info/LICENSE
lazylog_python-0.1.0.dist-info/METADATA
lazylog_python-0.1.0.dist-info/WHEEL
lazylog_python-0.1.0.dist-info/top_level.txt
lazylog_python-0.1.0.dist-info/RECORD
