Metadata-Version: 2.1
Name: lazylog-python
Version: 0.1.0
Summary: Lazylog Python Client
Home-page: https://github.com/gduverger/lazylog-python
Author: Georges Duverger
Author-email: georges.duverger@gmail.com
License: MIT
Platform: UNKNOWN
Classifier: Programming Language :: Python :: 3
Classifier: License :: OSI Approved :: MIT License
Classifier: Operating System :: OS Independent
Classifier: Intended Audience :: Developers
Classifier: Natural Language :: English
Requires-Python: >=3
